odoo/addons/so_report_hide_price_portal/README.rst
odoo/addons/so_report_hide_price_portal/__init__.py
odoo/addons/so_report_hide_price_portal/__manifest__.py
odoo/addons/so_report_hide_price_portal/readme/CONFIGURE.rst
odoo/addons/so_report_hide_price_portal/readme/DESCRIPTION.rst
odoo/addons/so_report_hide_price_portal/readme/README.rst
odoo/addons/so_report_hide_price_portal/readme/USAGE.rst
odoo/addons/so_report_hide_price_portal/static/description/icon.png
odoo/addons/so_report_hide_price_portal/static/description/index.html
odoo/addons/so_report_hide_price_portal/views/sale_portal_templates.xml
odoo_addon_so_report_hide_price_portal-15.0.1.0.0.2.dist-info/METADATA
odoo_addon_so_report_hide_price_portal-15.0.1.0.0.2.dist-info/WHEEL
odoo_addon_so_report_hide_price_portal-15.0.1.0.0.2.dist-info/top_level.txt
odoo_addon_so_report_hide_price_portal-15.0.1.0.0.2.dist-info/RECORD
